<Properties StartupConfiguration="{D36139BE-9FE2-47F1-B986-EC554D8BCC28}|Default">
  <MonoDevelop.Ide.Workbench ActiveDocument="LauroreJean_FinalProject/Assignment.cs">
    <Files>
      <File FileName="LauroreJean_FinalProject/Program.cs" Line="10" Column="45" />
      <File FileName="LauroreJean_FinalProject/Menu.cs" Line="30" Column="62" />
      <File FileName="LauroreJean_FinalProject/Validation.cs" Line="64" Column="69" />
      <File FileName="LauroreJean_FinalProject/Vehicle.cs" Line="27" Column="41" />
      <File FileName="LauroreJean_FinalProject/Car.cs" Line="12" Column="176" />
      <File FileName="LauroreJean_FinalProject/Helicopter.cs" Line="11" Column="184" />
      <File FileName="LauroreJean_FinalProject/Motorcycle.cs" Line="11" Column="184" />
      <File FileName="LauroreJean_FinalProject/Assignment.cs" Line="314" Column="144" />
    </Files>
    <Pads>
      <Pad Id="ProjectPad">
        <State name="__root__">
          <Node name="LauroreJean_FinalProject" expanded="True">
            <Node name="LauroreJean_FinalProject" expanded="True">
              <Node name="Assignment.cs" selected="True" />
            </Node>
          </Node>
        </State>
      </Pad>
    </Pads>
  </MonoDevelop.Ide.Workbench>
  <MonoDevelop.Ide.ItemProperties.LauroreJean__FinalProject PreferredExecutionTarget="MonoDevelop.Default" />
  <MonoDevelop.Ide.DebuggingService.PinnedWatches />
  <MonoDevelop.Ide.Workspace ActiveConfiguration="Debug" />
  <MonoDevelop.Ide.DebuggingService.Breakpoints>
    <BreakpointStore />
  </MonoDevelop.Ide.DebuggingService.Breakpoints>
  <MultiItemStartupConfigurations />
</Properties>